{
  "data": [
    {
      "id": 1,
      "first_name": "Olaf",
      "last_name": "Champlin",
      "email": "Aric47@hotmail.com"
    },
    {
      "id": 2,
      "first_name": "Earline",
      "last_name": "Schaefer",
      "email": "Orin_Wuckert66@hotmail.com"
    },
    {
      "id": 3,
      "first_name": "Torrance",
      "last_name": "Quigley",
      "email": "Meaghan76@hotmail.com"
    },
    {
      "id": 4,
      "first_name": "Luna",
      "last_name": "Lakin",
      "email": "Alize.Hammes@gmail.com"
    },
    {
      "id": 5,
      "first_name": "Alexander",
      "last_name": "Emard",
      "email": "Carole.Osinski18@yahoo.com"
    },
    {
      "id": 6,
      "first_name": "Kellen",
      "last_name": "Wisoky",
      "email": "Emanuel_Brown34@yahoo.com"
    },
    {
      "id": 7,
      "first_name": "Mervin",
      "last_name": "Krajcik",
      "email": "Geovanny.Turcotte@hotmail.com"
    },
    {
      "id": 8,
      "first_name": "Victoria",
      "last_name": "Brakus",
      "email": "Rupert_Barton@gmail.com"
    },
    {
      "id": 9,
      "first_name": "Karianne",
      "last_name": "Frami",
      "email": "Edmund35@hotmail.com"
    },
    {
      "id": 10,
      "first_name": "Vernie",
      "last_name": "Cartwright",
      "email": "Hobart.Zemlak@hotmail.com"
    },
    {
      "id": 11,
      "first_name": "Estevan",
      "last_name": "Lesch",
      "email": "Anais5@gmail.com"
    },
    {
      "id": 12,
      "first_name": "Nathen",
      "last_name": "McCullough",
      "email": "Keshaun.Gleason78@hotmail.com"
    },
    {
      "id": 13,
      "first_name": "Onie",
      "last_name": "Thompson",
      "email": "Deonte_Carroll45@gmail.com"
    },
    {
      "id": 14,
      "first_name": "Jaqueline",
      "last_name": "Hamill",
      "email": "Kiera85@gmail.com"
    },
    {
      "id": 15,
      "first_name": "Rylee",
      "last_name": "Aufderhar",
      "email": "Cathrine_Langworth@yahoo.com"
    },
    {
      "id": 16,
      "first_name": "Kobe",
      "last_name": "Schuppe",
      "email": "Garry_Dach94@gmail.com"
    },
    {
      "id": 17,
      "first_name": "Alan",
      "last_name": "McLaughlin",
      "email": "Jarred56@yahoo.com"
    },
    {
      "id": 18,
      "first_name": "Maegan",
      "last_name": "Price",
      "email": "Arely.Jenkins60@yahoo.com"
    },
    {
      "id": 19,
      "first_name": "Alicia",
      "last_name": "Von",
      "email": "Adelle_Cummerata@yahoo.com"
    },
    {
      "id": 20,
      "first_name": "Maxie",
      "last_name": "Gutmann",
      "email": "Mina_Gleichner@yahoo.com"
    },
    {
      "id": 21,
      "first_name": "Sylvia",
      "last_name": "Rolfson",
      "email": "Cullen.Toy73@yahoo.com"
    },
    {
      "id": 22,
      "first_name": "Aliya",
      "last_name": "Crona",
      "email": "Hassie82@hotmail.com"
    },
    {
      "id": 23,
      "first_name": "Amani",
      "last_name": "Rosenbaum",
      "email": "Timothy.Ankunding@yahoo.com"
    },
    {
      "id": 24,
      "first_name": "Celestino",
      "last_name": "Johns",
      "email": "Emmitt.Konopelski18@yahoo.com"
    },
    {
      "id": 25,
      "first_name": "Mia",
      "last_name": "Pollich",
      "email": "Everett_Marquardt@yahoo.com"
    },
    {
      "id": 26,
      "first_name": "Mia",
      "last_name": "Feest",
      "email": "Tyrell12@yahoo.com"
    },
    {
      "id": 27,
      "first_name": "Camryn",
      "last_name": "Schuster",
      "email": "Markus_Pouros44@hotmail.com"
    },
    {
      "id": 28,
      "first_name": "Letha",
      "last_name": "Stamm",
      "email": "Orrin.Hoeger@hotmail.com"
    },
    {
      "id": 29,
      "first_name": "Hazle",
      "last_name": "Tremblay",
      "email": "Anika86@gmail.com"
    },
    {
      "id": 30,
      "first_name": "Harmon",
      "last_name": "Larson",
      "email": "Citlalli47@gmail.com"
    },
    {
      "id": 31,
      "first_name": "Skyla",
      "last_name": "Spencer",
      "email": "Pink.Effertz49@hotmail.com"
    },
    {
      "id": 32,
      "first_name": "Brad",
      "last_name": "Dietrich",
      "email": "Clementine63@yahoo.com"
    },
    {
      "id": 33,
      "first_name": "Alyson",
      "last_name": "Schmeler",
      "email": "Ezra.Hand@yahoo.com"
    },
    {
      "id": 34,
      "first_name": "Brooklyn",
      "last_name": "Marvin",
      "email": "Reggie40@hotmail.com"
    },
    {
      "id": 35,
      "first_name": "Katharina",
      "last_name": "Rowe",
      "email": "Laisha.Huel90@yahoo.com"
    },
    {
      "id": 36,
      "first_name": "Wilson",
      "last_name": "Shanahan",
      "email": "Kathryn.Nolan10@gmail.com"
    },
    {
      "id": 37,
      "first_name": "Georgianna",
      "last_name": "Carroll",
      "email": "Ana78@yahoo.com"
    },
    {
      "id": 38,
      "first_name": "Alfred",
      "last_name": "Luettgen",
      "email": "Arthur_Kuvalis7@hotmail.com"
    },
    {
      "id": 39,
      "first_name": "Maiya",
      "last_name": "Heathcote",
      "email": "Shana.Cartwright38@yahoo.com"
    },
    {
      "id": 40,
      "first_name": "Claud",
      "last_name": "Johnson",
      "email": "Angus.Haag@gmail.com"
    },
    {
      "id": 41,
      "first_name": "Chad",
      "last_name": "Robel",
      "email": "Felicita35@gmail.com"
    },
    {
      "id": 42,
      "first_name": "Evelyn",
      "last_name": "Hodkiewicz",
      "email": "Nathaniel.Braun52@yahoo.com"
    },
    {
      "id": 43,
      "first_name": "Darrell",
      "last_name": "Langworth",
      "email": "Charley_Steuber3@gmail.com"
    },
    {
      "id": 44,
      "first_name": "Raymond",
      "last_name": "Dietrich",
      "email": "Deja.Cummings14@hotmail.com"
    },
    {
      "id": 45,
      "first_name": "Eldridge",
      "last_name": "Balistreri",
      "email": "Ronny.Rath42@gmail.com"
    },
    {
      "id": 46,
      "first_name": "Kobe",
      "last_name": "Lindgren",
      "email": "Birdie91@yahoo.com"
    },
    {
      "id": 47,
      "first_name": "Cassidy",
      "last_name": "Reichert",
      "email": "Destini94@yahoo.com"
    },
    {
      "id": 48,
      "first_name": "Clara",
      "last_name": "Gorczany",
      "email": "Virgil33@gmail.com"
    },
    {
      "id": 49,
      "first_name": "Sarina",
      "last_name": "Schumm",
      "email": "Nikita_Wiegand@yahoo.com"
    },
    {
      "id": 50,
      "first_name": "Yasmine",
      "last_name": "Jacobs",
      "email": "Lucile_Morar77@yahoo.com"
    },
    {
      "id": 51,
      "first_name": "Libby",
      "last_name": "Tremblay",
      "email": "Laverne62@yahoo.com"
    },
    {
      "id": 52,
      "first_name": "Vada",
      "last_name": "Willms",
      "email": "Pete_Wyman36@hotmail.com"
    },
    {
      "id": 53,
      "first_name": "Delilah",
      "last_name": "Crooks",
      "email": "Alexandro_Greenfelder@yahoo.com"
    },
    {
      "id": 54,
      "first_name": "Nolan",
      "last_name": "Jones",
      "email": "Agustina.Harber1@yahoo.com"
    },
    {
      "id": 55,
      "first_name": "Antwan",
      "last_name": "Jaskolski",
      "email": "Gerhard_Emmerich@gmail.com"
    },
    {
      "id": 56,
      "first_name": "Tito",
      "last_name": "Kunde",
      "email": "Fredy_Wehner@yahoo.com"
    },
    {
      "id": 57,
      "first_name": "Joaquin",
      "last_name": "Farrell",
      "email": "Keegan76@yahoo.com"
    },
    {
      "id": 58,
      "first_name": "Susana",
      "last_name": "Lueilwitz",
      "email": "Imelda44@gmail.com"
    },
    {
      "id": 59,
      "first_name": "Alexandrine",
      "last_name": "Weissnat",
      "email": "Abdul_Wilderman@gmail.com"
    },
    {
      "id": 60,
      "first_name": "Sheila",
      "last_name": "Bogan",
      "email": "Caitlyn.Casper11@hotmail.com"
    },
    {
      "id": 61,
      "first_name": "Ayden",
      "last_name": "Green",
      "email": "Gustave37@gmail.com"
    },
    {
      "id": 62,
      "first_name": "Jaquan",
      "last_name": "Ferry",
      "email": "Wilbert21@gmail.com"
    },
    {
      "id": 63,
      "first_name": "Estrella",
      "last_name": "Von",
      "email": "Eloy.Kemmer76@yahoo.com"
    },
    {
      "id": 64,
      "first_name": "Hanna",
      "last_name": "Schumm",
      "email": "Lea87@hotmail.com"
    },
    {
      "id": 65,
      "first_name": "Anissa",
      "last_name": "Hessel",
      "email": "Shanna12@hotmail.com"
    },
    {
      "id": 66,
      "first_name": "Garret",
      "last_name": "Rosenbaum",
      "email": "Violet_Ebert18@gmail.com"
    },
    {
      "id": 67,
      "first_name": "Gaylord",
      "last_name": "Witting",
      "email": "Katarina_Stanton36@yahoo.com"
    },
    {
      "id": 68,
      "first_name": "Zetta",
      "last_name": "Reynolds",
      "email": "Colleen99@yahoo.com"
    },
    {
      "id": 69,
      "first_name": "Consuelo",
      "last_name": "Williamson",
      "email": "Carole53@hotmail.com"
    },
    {
      "id": 70,
      "first_name": "Joany",
      "last_name": "Legros",
      "email": "Jovani.Mraz80@yahoo.com"
    },
    {
      "id": 71,
      "first_name": "Brenda",
      "last_name": "Funk",
      "email": "Zula15@yahoo.com"
    },
    {
      "id": 72,
      "first_name": "Kris",
      "last_name": "Schimmel",
      "email": "Gage32@hotmail.com"
    },
    {
      "id": 73,
      "first_name": "Gonzalo",
      "last_name": "Cartwright",
      "email": "Autumn.Donnelly63@gmail.com"
    },
    {
      "id": 74,
      "first_name": "Josiane",
      "last_name": "Bins",
      "email": "Enrico_Leannon11@hotmail.com"
    },
    {
      "id": 75,
      "first_name": "Dallas",
      "last_name": "Bruen",
      "email": "Enid.Hand@yahoo.com"
    },
    {
      "id": 76,
      "first_name": "Mazie",
      "last_name": "Schneider",
      "email": "Thomas.Heaney65@hotmail.com"
    },
    {
      "id": 77,
      "first_name": "Jaqueline",
      "last_name": "Lehner",
      "email": "Jamey48@yahoo.com"
    },
    {
      "id": 78,
      "first_name": "Mack",
      "last_name": "Macejkovic",
      "email": "Bart.Ferry@gmail.com"
    },
    {
      "id": 79,
      "first_name": "Destiny",
      "last_name": "Mante",
      "email": "Bradford_Becker@hotmail.com"
    },
    {
      "id": 80,
      "first_name": "Weldon",
      "last_name": "Crist",
      "email": "Mona_Cremin@gmail.com"
    },
    {
      "id": 81,
      "first_name": "Maximilian",
      "last_name": "Gusikowski",
      "email": "Dangelo.Funk@gmail.com"
    },
    {
      "id": 82,
      "first_name": "Janick",
      "last_name": "Zulauf",
      "email": "Vernice50@yahoo.com"
    },
    {
      "id": 83,
      "first_name": "Lenny",
      "last_name": "Koss",
      "email": "Claudia74@hotmail.com"
    },
    {
      "id": 84,
      "first_name": "Vaughn",
      "last_name": "Renner",
      "email": "Keven.Larson@hotmail.com"
    },
    {
      "id": 85,
      "first_name": "Deontae",
      "last_name": "Padberg",
      "email": "Tyrique_Lehner@hotmail.com"
    },
    {
      "id": 86,
      "first_name": "Leda",
      "last_name": "Swaniawski",
      "email": "Stephany_Gutkowski76@hotmail.com"
    },
    {
      "id": 87,
      "first_name": "Dixie",
      "last_name": "Buckridge",
      "email": "Tyshawn51@gmail.com"
    },
    {
      "id": 88,
      "first_name": "Iliana",
      "last_name": "Ebert",
      "email": "Eleonore.Erdman38@yahoo.com"
    },
    {
      "id": 89,
      "first_name": "Reagan",
      "last_name": "Quigley",
      "email": "Alfreda20@yahoo.com"
    },
    {
      "id": 90,
      "first_name": "Abbigail",
      "last_name": "Veum",
      "email": "Jared_Kohler32@yahoo.com"
    },
    {
      "id": 91,
      "first_name": "Vicenta",
      "last_name": "Yost",
      "email": "Rory_Reinger@yahoo.com"
    },
    {
      "id": 92,
      "first_name": "Bertram",
      "last_name": "Pacocha",
      "email": "Danyka9@gmail.com"
    },
    {
      "id": 93,
      "first_name": "Grace",
      "last_name": "Ledner",
      "email": "Terrance57@gmail.com"
    },
    {
      "id": 94,
      "first_name": "Fannie",
      "last_name": "Hartmann",
      "email": "Kim.Watsica27@yahoo.com"
    },
    {
      "id": 95,
      "first_name": "Kobe",
      "last_name": "Bartoletti",
      "email": "Rickey26@gmail.com"
    },
    {
      "id": 96,
      "first_name": "Annabel",
      "last_name": "Sipes",
      "email": "Hyman_Doyle@yahoo.com"
    },
    {
      "id": 97,
      "first_name": "Nils",
      "last_name": "Roob",
      "email": "Sydney.Ullrich24@yahoo.com"
    },
    {
      "id": 98,
      "first_name": "Savion",
      "last_name": "Bernier",
      "email": "Margot47@yahoo.com"
    },
    {
      "id": 99,
      "first_name": "Krystel",
      "last_name": "Auer",
      "email": "Hettie_Kirlin68@gmail.com"
    },
    {
      "id": 100,
      "first_name": "Johann",
      "last_name": "Koelpin",
      "email": "Alysha_Moen@yahoo.com"
    }
  ]
}
